{
  "fetched_at": "2026-04-14T06:12:39.951017+00:00",
  "refresh_after": "2026-04-28T06:12:39.951017+00:00",
  "source_signature": "cb7b47c358c4b5cdd9d60bde9a721e60e31bdb4f088d85a8d9976e921b5d8c29",
  "configured_source_url": "https://maps.app.goo.gl/HGxndKFgJNiVjZRL7",
  "source_url": "https://maps.app.goo.gl/HGxndKFgJNiVjZRL7",
  "list_id": "lGgt3zsnSgSpSrxbO_ia3g",
  "title": "Melbourne, Australia 🇦🇺",
  "description": "Michael’s Melbourne, Australia 🇦🇺 bookmarks. See https://beacons.ai/demflyers for more, or follow on Instagram / Threads / BlueSky @demflyers",
  "places": [
    {
      "name": "Bianchetto",
      "address": "26-28 Cotham Rd, Kew VIC 3101, Australia",
      "note": null,
      "is_favorite": false,
      "lat": -37.8070131,
      "lng": 145.03137049999998,
      "maps_url": "https://maps.google.com/?cid=7698414859055537019",
      "cid": "7698414859055537019",
      "google_id": "/g/11vs80dn9d"
    },
    {
      "name": "Wally's Albert Park",
      "address": "67 Cardigan Pl, Albert Park VIC 3206, Australia",
      "note": null,
      "is_favorite": false,
      "lat": -37.841174599999995,
      "lng": 144.9533792,
      "maps_url": "https://maps.google.com/?cid=7698453964550688259",
      "cid": "7698453964550688259",
      "google_id": "/g/11y3k4_0kq"
    },
    {
      "name": "Sardinas",
      "address": "688 High St, Reservoir VIC 3073, Australia",
      "note": null,
      "is_favorite": false,
      "lat": -37.7286287,
      "lng": 145.00578389999998,
      "maps_url": "https://maps.google.com/?cid=7698416806983727009",
      "cid": "7698416806983727009",
      "google_id": "/g/11l296t0b1"
    },
    {
      "name": "Gracie's Wine Room",
      "address": "27 Toorak Rd, South Yarra VIC 3141, Australia",
      "note": null,
      "is_favorite": false,
      "lat": -37.838227499999995,
      "lng": 144.9874109,
      "maps_url": "https://maps.google.com/?cid=7698414424517905819",
      "cid": "7698414424517905819",
      "google_id": "/g/11wx6ctp_5"
    },
    {
      "name": "Oakridge Wines",
      "address": "864 Maroondah Hwy, Coldstream VIC 3770, Australia",
      "note": null,
      "is_favorite": false,
      "lat": -37.6878053,
      "lng": 145.4575995,
      "maps_url": "https://maps.google.com/?cid=7698856443437633233",
      "cid": "7698856443437633233",
      "google_id": "/g/1vlqqbqx"
    },
    {
      "name": "Sogumm",
      "address": "466 Church St, Cremorne VIC 3121, Australia",
      "note": null,
      "is_favorite": false,
      "lat": -37.8262491,
      "lng": 144.99757879999999,
      "maps_url": "https://maps.google.com/?cid=7698415117527596813",
      "cid": "7698415117527596813",
      "google_id": "/g/11x7zs_th1"
    },
    {
      "name": "Baguette Studios",
      "address": "15-27 Wreckyn St, North Melbourne VIC 3051, Australia",
      "note": null,
      "is_favorite": false,
      "lat": -37.800503299999995,
      "lng": 144.95366479999998,
      "maps_url": "https://maps.google.com/?cid=7698443828257498517",
      "cid": "7698443828257498517",
      "google_id": "/g/11rfbkbp9l"
    },
    {
      "name": "1pluspiece Cafe",
      "address": "266 Whitehorse Rd, Balwyn VIC 3103, Australia",
      "note": null,
      "is_favorite": false,
      "lat": -37.813136,
      "lng": 145.082277,
      "maps_url": "https://maps.google.com/?cid=7698412342569732559",
      "cid": "7698412342569732559",
      "google_id": "/g/11b75mh4hg"
    },
    {
      "name": "Aperitivo Bar Ristorante",
      "address": "275 Lygon St, Carlton VIC 3053, Australia",
      "note": null,
      "is_favorite": false,
      "lat": -37.799043399999995,
      "lng": 144.9670552,
      "maps_url": "https://maps.google.com/?cid=7698415003176553759",
      "cid": "7698415003176553759",
      "google_id": "/g/11j2356pr8"
    },
    {
      "name": "Alimentari",
      "address": "251 Brunswick St, Fitzroy VIC 3065, Australia",
      "note": null,
      "is_favorite": false,
      "lat": -37.7997186,
      "lng": 144.9780663,
      "maps_url": "https://maps.google.com/?cid=7698414139861373543",
      "cid": "7698414139861373543",
      "google_id": "/g/1q2w3t_t8"
    },
    {
      "name": "Operator25",
      "address": "25 Wills St, Melbourne VIC 3000, Australia",
      "note": null,
      "is_favorite": false,
      "lat": -37.8106796,
      "lng": 144.95698919999998,
      "maps_url": "https://maps.google.com/?cid=7698443187404101637",
      "cid": "7698443187404101637",
      "google_id": "/g/12mkvn50v"
    },
    {
      "name": "Soul Soul Cafe",
      "address": "shop 1/158 Victoria St, Carlton VIC 3053, Australia",
      "note": null,
      "is_favorite": false,
      "lat": -37.8063351,
      "lng": 144.9619078,
      "maps_url": "https://maps.google.com/?cid=7698414983860889671",
      "cid": "7698414983860889671",
      "google_id": "/g/11qr813n5t"
    },
    {
      "name": "Khabbay Restaurant",
      "address": "140-146 Lygon St, Carlton VIC 3053, Australia",
      "note": null,
      "is_favorite": false,
      "lat": -37.8038169,
      "lng": 144.966678,
      "maps_url": "https://maps.google.com/?cid=7698415280706887085",
      "cid": "7698415280706887085",
      "google_id": "/g/11g4dythmj"
    },
    {
      "name": "Ziyka Restaurant",
      "address": "234-236 Lygon St, Carlton VIC 3053, Australia",
      "note": null,
      "is_favorite": false,
      "lat": -37.8016796,
      "lng": 144.9672055,
      "maps_url": "https://maps.google.com/?cid=7698414452468041633",
      "cid": "7698414452468041633",
      "google_id": "/g/11b5ythw1y"
    },
    {
      "name": "Pidapipó Carlton",
      "address": "299 Lygon St, Carlton VIC 3053, Australia",
      "note": null,
      "is_favorite": false,
      "lat": -37.7983202,
      "lng": 144.9671769,
      "maps_url": "https://maps.google.com/?cid=7698414102535671123",
      "cid": "7698414102535671123",
      "google_id": "/g/11b6hyrjvb"
    },
    {
      "name": "Higher Ground",
      "address": "650 Little Bourke St, Melbourne VIC 3000, Australia",
      "note": null,
      "is_favorite": false,
      "lat": -37.8158034,
      "lng": 144.9530273,
      "maps_url": "https://maps.google.com/?cid=7698443206922280953",
      "cid": "7698443206922280953",
      "google_id": "/g/11cm00hnch"
    },
    {
      "name": "KATA KITA",
      "address": null,
      "note": null,
      "is_favorite": false,
      "lat": -37.809977499999995,
      "lng": 144.9620272,
      "maps_url": "https://maps.google.com/?cid=7698414734372236921",
      "cid": "7698414734372236921",
      "google_id": null
    },
    {
      "name": "Market Lane Coffee - Dairy Hall, QVM",
      "address": "Shop 73-76 Dairy Produce Hall Queen Victoria Market, Melbourne VIC 3000, Australia",
      "note": null,
      "is_favorite": false,
      "lat": -37.8067018,
      "lng": 144.95915499999998,
      "maps_url": "https://maps.google.com/?cid=7698443492074818035",
      "cid": "7698443492074818035",
      "google_id": "/g/11h4kgphp2"
    },
    {
      "name": "Axil Coffee Roasters Flinders Gate",
      "address": "180 Flinders St, Melbourne VIC 3000, Australia",
      "note": null,
      "is_favorite": false,
      "lat": -37.8169329,
      "lng": 144.9686883,
      "maps_url": "https://maps.google.com/?cid=7698415240291813507",
      "cid": "7698415240291813507",
      "google_id": "/g/11lt48wr1n"
    },
    {
      "name": "Brother Baba Budan",
      "address": "359 Little Bourke St, Melbourne VIC 3000, Australia",
      "note": null,
      "is_favorite": false,
      "lat": -37.813541,
      "lng": 144.9620988,
      "maps_url": "https://maps.google.com/?cid=7698413959147311849",
      "cid": "7698413959147311849",
      "google_id": "/g/1v76zsyt"
    },
    {
      "name": "BENCH COFFEE CO. Lt Collins",
      "address": "321 Little Collins St, Melbourne VIC 3000, Australia",
      "note": null,
      "is_favorite": false,
      "lat": -37.8151891,
      "lng": 144.96418599999998,
      "maps_url": "https://maps.google.com/?cid=7698414654808430365",
      "cid": "7698414654808430365",
      "google_id": "/g/11ng15yshv"
    },
    {
      "name": "Queen Victoria Market, Queen St, Melbourne VIC 3000, Australia",
      "address": "Queen St, Melbourne VIC 3000, Australia",
      "note": null,
      "is_favorite": false,
      "lat": -37.8075798,
      "lng": 144.956785,
      "maps_url": "https://maps.google.com/?cid=7698443091888330673",
      "cid": "7698443091888330673",
      "google_id": null
    },
    {
      "name": "Moonlit Sanctuary Wildlife Conservation Park",
      "address": null,
      "note": null,
      "is_favorite": false,
      "lat": -38.2110707,
      "lng": 145.2508389,
      "maps_url": "https://maps.google.com/?cid=7698351337735031907",
      "cid": "7698351337735031907",
      "google_id": null
    },
    {
      "name": "The Dojo Ramen Bar",
      "address": "333 High St, Northcote VIC 3070, Australia",
      "note": null,
      "is_favorite": false,
      "lat": -37.7706751,
      "lng": 144.998534,
      "maps_url": "https://maps.google.com/?cid=7698414820665853407",
      "cid": "7698414820665853407",
      "google_id": "/g/1pwfy17nj"
    },
    {
      "name": "Level 3 Nightclubs",
      "address": null,
      "note": null,
      "is_favorite": false,
      "lat": -37.823436799999996,
      "lng": 144.9580861,
      "maps_url": "https://maps.google.com/?cid=7698443224181130231",
      "cid": "7698443224181130231",
      "google_id": null
    },
    {
      "name": "ShanDong MaMa",
      "address": null,
      "note": null,
      "is_favorite": false,
      "lat": -37.8125308,
      "lng": 144.9673157,
      "maps_url": "https://maps.google.com/?cid=7698414046555770903",
      "cid": "7698414046555770903",
      "google_id": null
    },
    {
      "name": "Shinwa Izakaya",
      "address": "139 Sydney Rd, Brunswick VIC 3056, Australia",
      "note": null,
      "is_favorite": false,
      "lat": -37.7741221,
      "lng": 144.9608003,
      "maps_url": "https://maps.google.com/?cid=7698442546951905441",
      "cid": "7698442546951905441",
      "google_id": "/g/1q6j8vx8t"
    },
    {
      "name": "Phờ Nom Collins St",
      "address": null,
      "note": null,
      "is_favorite": false,
      "lat": -37.8187861,
      "lng": 144.9558269,
      "maps_url": "https://maps.google.com/?cid=7698443202564167489",
      "cid": "7698443202564167489",
      "google_id": null
    },
    {
      "name": "Common Galaxia",
      "address": "3/130 Victoria St, Seddon VIC 3011, Australia",
      "note": null,
      "is_favorite": false,
      "lat": -37.8041108,
      "lng": 144.8921332,
      "maps_url": "https://maps.google.com/?cid=7698443917099549737",
      "cid": "7698443917099549737",
      "google_id": "/g/12cnyrh3_"
    },
    {
      "name": "Rudimentary",
      "address": "16-20 Leeds St, Footscray VIC 3011, Australia",
      "note": null,
      "is_favorite": false,
      "lat": -37.7981549,
      "lng": 144.9011105,
      "maps_url": "https://maps.google.com/?cid=7698443492468302021",
      "cid": "7698443492468302021",
      "google_id": "/g/11b7hll3v1"
    },
    {
      "name": "Blackcat Fitzroy",
      "address": "252 Brunswick St, Fitzroy VIC 3065, Australia",
      "note": null,
      "is_favorite": false,
      "lat": -37.7999139,
      "lng": 144.97835,
      "maps_url": "https://maps.google.com/?cid=7698414139752273755",
      "cid": "7698414139752273755",
      "google_id": "/g/1tjhxt3b"
    },
    {
      "name": "Shop Ramen",
      "address": "329 Smith St, Fitzroy VIC 3065, Australia",
      "note": null,
      "is_favorite": false,
      "lat": -37.7992383,
      "lng": 144.98409189999998,
      "maps_url": "https://maps.google.com/?cid=7698414415876398499",
      "cid": "7698414415876398499",
      "google_id": "/g/11b6328hyj"
    },
    {
      "name": "Hector's Deli",
      "address": "111 Moor St, Fitzroy VIC 3065, Australia",
      "note": null,
      "is_favorite": false,
      "lat": -37.801600199999996,
      "lng": 144.9786743,
      "maps_url": "https://maps.google.com/?cid=7698414703559666899",
      "cid": "7698414703559666899",
      "google_id": "/g/11sbs8xh7g"
    },
    {
      "name": "Seven Seeds Coffee Roasters",
      "address": "114 Berkeley St, Carlton VIC 3053, Australia",
      "note": null,
      "is_favorite": false,
      "lat": -37.8029711,
      "lng": 144.95900269999998,
      "maps_url": "https://maps.google.com/?cid=7698443084823518397",
      "cid": "7698443084823518397",
      "google_id": "/g/1tcyxkm9"
    },
    {
      "name": "Hecho en Mexico Fitzroy",
      "address": "326 Brunswick St, Fitzroy VIC 3065, Australia",
      "note": null,
      "is_favorite": false,
      "lat": -37.797492999999996,
      "lng": 144.978841,
      "maps_url": "https://maps.google.com/?cid=7698414421053774579",
      "cid": "7698414421053774579",
      "google_id": "/g/1ptxbbj0v"
    },
    {
      "name": "Bon Ap' Petit Bistro",
      "address": "193 Brunswick St, Fitzroy VIC 3065, Australia",
      "note": null,
      "is_favorite": false,
      "lat": -37.8017392,
      "lng": 144.9777499,
      "maps_url": "https://maps.google.com/?cid=7698414113657825495",
      "cid": "7698414113657825495",
      "google_id": "/g/11cjhbc6x6"
    },
    {
      "name": "Uptown Jazz Cafe",
      "address": "1/177 Brunswick St, Fitzroy VIC 3065, Australia",
      "note": null,
      "is_favorite": false,
      "lat": -37.8021402,
      "lng": 144.9775539,
      "maps_url": "https://maps.google.com/?cid=7698414137689937153",
      "cid": "7698414137689937153",
      "google_id": "/g/1hf4shkzx"
    },
    {
      "name": "Black Pearl",
      "address": "304 Brunswick St, Fitzroy VIC 3065, Australia",
      "note": null,
      "is_favorite": false,
      "lat": -37.7980522,
      "lng": 144.9786306,
      "maps_url": "https://maps.google.com/?cid=7698414420964311983",
      "cid": "7698414420964311983",
      "google_id": "/g/1tg9n8f4"
    },
    {
      "name": "Auction Rooms",
      "address": null,
      "note": null,
      "is_favorite": false,
      "lat": -37.802501299999996,
      "lng": 144.94948829999998,
      "maps_url": "https://maps.google.com/?cid=7698443116964316929",
      "cid": "7698443116964316929",
      "google_id": null
    },
    {
      "name": "Chaise Lounge",
      "address": null,
      "note": null,
      "is_favorite": false,
      "lat": -37.816116,
      "lng": 144.960926,
      "maps_url": "https://maps.google.com/?cid=7698443191148915357",
      "cid": "7698443191148915357",
      "google_id": null
    },
    {
      "name": "Laksa King",
      "address": "6-12 Pin Oak Cres, Flemington VIC 3031, Australia",
      "note": null,
      "is_favorite": false,
      "lat": -37.7878742,
      "lng": 144.9295306,
      "maps_url": "https://maps.google.com/?cid=7698443841612212625",
      "cid": "7698443841612212625",
      "google_id": "/g/1tnbl8d2"
    },
    {
      "name": "Degraves St",
      "address": "Melbourne VIC 3000",
      "note": null,
      "is_favorite": false,
      "lat": -37.817315199999996,
      "lng": 144.9658047,
      "maps_url": "https://maps.google.com/?cid=7698413954168687745",
      "cid": "7698413954168687745",
      "google_id": null
    },
    {
      "name": "Little Ramen Bar",
      "address": null,
      "note": null,
      "is_favorite": false,
      "lat": -37.8156807,
      "lng": 144.9626968,
      "maps_url": "https://maps.google.com/?cid=7698413959285667141",
      "cid": "7698413959285667141",
      "google_id": null
    },
    {
      "name": "The Kettle Black",
      "address": "50 Albert Rd, South Melbourne VIC 3205, Australia",
      "note": null,
      "is_favorite": false,
      "lat": -37.834078399999996,
      "lng": 144.97133829999999,
      "maps_url": "https://maps.google.com/?cid=7698454973649017517",
      "cid": "7698454973649017517",
      "google_id": "/g/11b6wj5pvl"
    },
    {
      "name": "Shanghai Street",
      "address": null,
      "note": null,
      "is_favorite": false,
      "lat": -37.8115563,
      "lng": 144.9683296,
      "maps_url": "https://maps.google.com/?cid=7698414053318760461",
      "cid": "7698414053318760461",
      "google_id": null
    },
    {
      "name": "Shujinko Russell",
      "address": null,
      "note": null,
      "is_favorite": false,
      "lat": -37.811283599999996,
      "lng": 144.9672186,
      "maps_url": "https://maps.google.com/?cid=7698414046170573763",
      "cid": "7698414046170573763",
      "google_id": null
    },
    {
      "name": "Rice Workshop Melbourne",
      "address": null,
      "note": null,
      "is_favorite": false,
      "lat": -37.8122184,
      "lng": 144.96579749999998,
      "maps_url": "https://maps.google.com/?cid=7698414049419445515",
      "cid": "7698414049419445515",
      "google_id": null
    },
    {
      "name": "Yaowarat",
      "address": null,
      "note": null,
      "is_favorite": false,
      "lat": -37.8116564,
      "lng": 144.9669702,
      "maps_url": "https://maps.google.com/?cid=7698414514776473883",
      "cid": "7698414514776473883",
      "google_id": null
    },
    {
      "name": "Roccella Italian Restaurant East Melbourne",
      "address": "158 Clarendon St, East Melbourne VIC 3002, Australia",
      "note": null,
      "is_favorite": false,
      "lat": -37.8119728,
      "lng": 144.98354039999998,
      "maps_url": "https://maps.google.com/?cid=7698414650796041865",
      "cid": "7698414650796041865",
      "google_id": "/g/11j3s5sh_x"
    },
    {
      "name": "The Evelyn Hotel",
      "address": "351 Brunswick St, Fitzroy VIC 3065, Australia",
      "note": null,
      "is_favorite": false,
      "lat": -37.796619,
      "lng": 144.9785765,
      "maps_url": "https://maps.google.com/?cid=7698414422608732731",
      "cid": "7698414422608732731",
      "google_id": "/g/1tk8nr0v"
    },
    {
      "name": "Mukka Indian Restaurant Fitzroy",
      "address": "366 Brunswick St, Fitzroy VIC 3065, Australia",
      "note": null,
      "is_favorite": false,
      "lat": -37.796358999999995,
      "lng": 144.97903399999998,
      "maps_url": "https://maps.google.com/?cid=7698414423042099131",
      "cid": "7698414423042099131",
      "google_id": "/g/11bwkq80lb"
    },
    {
      "name": "Vegie Bar",
      "address": "380 Brunswick St, Fitzroy VIC 3065, Australia",
      "note": null,
      "is_favorite": false,
      "lat": -37.795847599999995,
      "lng": 144.9791008,
      "maps_url": "https://maps.google.com/?cid=7698414422406290393",
      "cid": "7698414422406290393",
      "google_id": "/g/1tgfdhvt"
    },
    {
      "name": "Tall Timber Cafe",
      "address": "60 Commercial Rd, Prahran VIC 3181, Australia",
      "note": null,
      "is_favorite": false,
      "lat": -37.8461723,
      "lng": 144.98813719999998,
      "maps_url": "https://maps.google.com/?cid=7698455114808003885",
      "cid": "7698455114808003885",
      "google_id": "/g/11b60d5k7h"
    },
    {
      "name": "Inkerman Hotel",
      "address": "375 Inkerman St, St Kilda East VIC 3183, Australia",
      "note": null,
      "is_favorite": false,
      "lat": -37.8663084,
      "lng": 144.99794409999998,
      "maps_url": "https://maps.google.com/?cid=7698455276655151135",
      "cid": "7698455276655151135",
      "google_id": "/g/1tqyfn6f"
    },
    {
      "name": "Batch Espresso",
      "address": "Shop 1/320 Carlisle St, Balaclava VIC 3183, Australia",
      "note": null,
      "is_favorite": false,
      "lat": -37.8688931,
      "lng": 144.9952004,
      "maps_url": "https://maps.google.com/?cid=7698455304086025589",
      "cid": "7698455304086025589",
      "google_id": "/g/1tf7gtjq"
    },
    {
      "name": "Monk Bodhi Dharma",
      "address": "Rear, 202 Carlisle St, Balaclava VIC 3183, Australia",
      "note": null,
      "is_favorite": false,
      "lat": -37.868003,
      "lng": 144.99085549999998,
      "maps_url": "https://maps.google.com/?cid=7698455257970641423",
      "cid": "7698455257970641423",
      "google_id": "/g/1w4f87km"
    },
    {
      "name": "Two Birds One Stone Cafe South Yarra",
      "address": "12 Claremont St, South Yarra VIC 3141, Australia",
      "note": null,
      "is_favorite": false,
      "lat": -37.8380083,
      "lng": 144.9940885,
      "maps_url": "https://maps.google.com/?cid=7698415014133186927",
      "cid": "7698415014133186927",
      "google_id": "/g/11cfdc3zj"
    },
    {
      "name": "Top Paddock Cafe",
      "address": "658 Church St, Richmond VIC 3121, Australia",
      "note": null,
      "is_favorite": false,
      "lat": -37.8327859,
      "lng": 144.9964075,
      "maps_url": "https://maps.google.com/?cid=7698413753534968277",
      "cid": "7698413753534968277",
      "google_id": "/g/12lktcc8k"
    },
    {
      "name": "Soi 38 Melbourne",
      "address": "38 Royal Ln, Melbourne VIC 3000, Australia",
      "note": null,
      "is_favorite": false,
      "lat": -37.8138765,
      "lng": 144.9669012,
      "maps_url": "https://maps.google.com/?cid=7698414042369842221",
      "cid": "7698414042369842221",
      "google_id": "/g/11cncb1rvc"
    },
    {
      "name": "Mr Ramen San",
      "address": "12a/200 Bourke St, Melbourne VIC 3000, Australia",
      "note": null,
      "is_favorite": false,
      "lat": -37.812401,
      "lng": 144.96724799999998,
      "maps_url": "https://maps.google.com/?cid=7698414046500150133",
      "cid": "7698414046500150133",
      "google_id": "/g/11b8jd1mkq"
    },
    {
      "name": "Heartbreaker",
      "address": "234A Russell St, Melbourne VIC 3000, Australia",
      "note": null,
      "is_favorite": false,
      "lat": -37.8109284,
      "lng": 144.96750459999998,
      "maps_url": "https://maps.google.com/?cid=7698414045965254527",
      "cid": "7698414045965254527",
      "google_id": "/g/11bysjp_9f"
    },
    {
      "name": "/m/026v2_h",
      "address": "17 Market Ln, Melbourne VIC 3000, Australia",
      "note": null,
      "is_favorite": false,
      "lat": -37.8118772,
      "lng": 144.96924579999998,
      "maps_url": "https://maps.google.com/?cid=7698414044167099311",
      "cid": "7698414044167099311",
      "google_id": null
    },
    {
      "name": "Bombabar",
      "address": "103 Lonsdale St, Melbourne VIC 3000, Australia",
      "note": null,
      "is_favorite": false,
      "lat": -37.8104041,
      "lng": 144.9691967,
      "maps_url": "https://maps.google.com/?cid=7698414044883853815",
      "cid": "7698414044883853815",
      "google_id": "/g/1pwfy2ykt"
    },
    {
      "name": "Fancy Hank's Barbecue Restaurant",
      "address": "1/79 Bourke St, Melbourne VIC 3000, Australia",
      "note": null,
      "is_favorite": false,
      "lat": -37.81217,
      "lng": 144.971057,
      "maps_url": "https://maps.google.com/?cid=7698413956845797267",
      "cid": "7698413956845797267",
      "google_id": "/g/11b6msn3xf"
    },
    {
      "name": "1806",
      "address": "169 Exhibition St, Melbourne VIC 3000, Australia",
      "note": null,
      "is_favorite": false,
      "lat": -37.811658099999995,
      "lng": 144.97007969999999,
      "maps_url": "https://maps.google.com/?cid=7698414043658903009",
      "cid": "7698414043658903009",
      "google_id": "/g/1tg86svh"
    },
    {
      "name": "HuTong",
      "address": "14-16 Market Ln, Melbourne VIC 3000, Australia",
      "note": null,
      "is_favorite": false,
      "lat": -37.811880599999995,
      "lng": 144.969389,
      "maps_url": "https://maps.google.com/?cid=7698414044047795985",
      "cid": "7698414044047795985",
      "google_id": "/g/1wrtc_9l"
    },
    {
      "name": "Gami Chicken & Beer",
      "address": "100 Little Lonsdale St, Melbourne VIC 3000, Australia",
      "note": null,
      "is_favorite": false,
      "lat": -37.809201099999996,
      "lng": 144.9687461,
      "maps_url": "https://maps.google.com/?cid=7698414045051516709",
      "cid": "7698414045051516709",
      "google_id": "/g/1v2yy_mc"
    },
    {
      "name": "Grain Store",
      "address": "517 Flinders Ln, Melbourne VIC 3000, Australia",
      "note": null,
      "is_favorite": false,
      "lat": -37.8196089,
      "lng": 144.9566558,
      "maps_url": "https://maps.google.com/?cid=7698443202415020305",
      "cid": "7698443202415020305",
      "google_id": "/g/12hlvchfy"
    },
    {
      "name": "Heartattack and Vine",
      "address": null,
      "note": null,
      "is_favorite": false,
      "lat": -37.7976457,
      "lng": 144.9672841,
      "maps_url": "https://maps.google.com/?cid=7698414102198457111",
      "cid": "7698414102198457111",
      "google_id": null
    },
    {
      "name": "Healesville Sanctuary (Zoos Victoria)",
      "address": null,
      "note": null,
      "is_favorite": false,
      "lat": -37.681616,
      "lng": 145.5298812,
      "maps_url": "https://maps.google.com/?cid=7721468109719440307",
      "cid": "7721468109719440307",
      "google_id": null
    },
    {
      "name": "Wax Music Lounge",
      "address": null,
      "note": null,
      "is_favorite": false,
      "lat": -37.8176892,
      "lng": 144.9660972,
      "maps_url": "https://maps.google.com/?cid=7698415183209388239",
      "cid": "7698415183209388239",
      "google_id": null
    },
    {
      "name": "Waxflower",
      "address": null,
      "note": null,
      "is_favorite": false,
      "lat": -37.7756918,
      "lng": 144.9707362,
      "maps_url": "https://maps.google.com/?cid=7698414488031372927",
      "cid": "7698414488031372927",
      "google_id": null
    },
    {
      "name": "Robot Bar",
      "address": "12 Bligh Pl, Melbourne VIC 3000, Australia",
      "note": null,
      "is_favorite": false,
      "lat": -37.817070099999995,
      "lng": 144.9637152,
      "maps_url": "https://maps.google.com/?cid=7698413956162637323",
      "cid": "7698413956162637323",
      "google_id": "/g/1v7tlj1_"
    },
    {
      "name": "Cookie",
      "address": "252 Swanston St, Melbourne VIC 3000, Australia",
      "note": null,
      "is_favorite": false,
      "lat": -37.812005299999996,
      "lng": 144.965164,
      "maps_url": "https://maps.google.com/?cid=7698414049491324975",
      "cid": "7698414049491324975",
      "google_id": "/g/1pzxq38rt"
    },
    {
      "name": "Manchuria",
      "address": "Level 1/7-9 Waratah Pl, Melbourne VIC 3000, Australia",
      "note": null,
      "is_favorite": false,
      "lat": -37.8116579,
      "lng": 144.9671022,
      "maps_url": "https://maps.google.com/?cid=7698414046116140839",
      "cid": "7698414046116140839",
      "google_id": "/g/1tfzb9yb"
    },
    {
      "name": "Union Club Hotel",
      "address": null,
      "note": null,
      "is_favorite": false,
      "lat": -37.803902799999996,
      "lng": 144.9823278,
      "maps_url": "https://maps.google.com/?cid=7698414134666314409",
      "cid": "7698414134666314409",
      "google_id": null
    },
    {
      "name": "Pepe's Italian & Liquor",
      "address": null,
      "note": null,
      "is_favorite": false,
      "lat": -37.8092788,
      "lng": 144.969035,
      "maps_url": "https://maps.google.com/?cid=7698415052726660491",
      "cid": "7698415052726660491",
      "google_id": null
    },
    {
      "name": "Berlin Bar",
      "address": "Level 2/16 Corrs Ln, Melbourne VIC 3000, Australia",
      "note": null,
      "is_favorite": false,
      "lat": -37.811130899999995,
      "lng": 144.9684355,
      "maps_url": "https://maps.google.com/?cid=7698414044420644185",
      "cid": "7698414044420644185",
      "google_id": "/g/1tcyrzj1"
    },
    {
      "name": "Hakata Gensuke Tonkotsu Ramen",
      "address": "168 Russell St, Melbourne VIC 3000, Australia",
      "note": null,
      "is_favorite": false,
      "lat": -37.812275,
      "lng": 144.968152,
      "maps_url": "https://maps.google.com/?cid=7698414046812264167",
      "cid": "7698414046812264167",
      "google_id": "/g/11b5wlw67c"
    },
    {
      "name": "Shanghai Street",
      "address": null,
      "note": null,
      "is_favorite": false,
      "lat": -37.8132447,
      "lng": 144.9623953,
      "maps_url": "https://maps.google.com/?cid=7698413959294513201",
      "cid": "7698413959294513201",
      "google_id": null
    },
    {
      "name": "Rice Paper Scissors",
      "address": null,
      "note": null,
      "is_favorite": false,
      "lat": -37.8142795,
      "lng": 144.9614222,
      "maps_url": "https://maps.google.com/?cid=7698414042918558451",
      "cid": "7698414042918558451",
      "google_id": null
    },
    {
      "name": "Meatmaiden",
      "address": "195 Little Collins St, Melbourne VIC 3000, Australia",
      "note": null,
      "is_favorite": false,
      "lat": -37.814305,
      "lng": 144.96776069999999,
      "maps_url": "https://maps.google.com/?cid=7698413964323265149",
      "cid": "7698413964323265149",
      "google_id": "/g/11bbw_kxlq"
    },
    {
      "name": "Hosier Ln",
      "address": "Melbourne VIC 3000, Australia",
      "note": null,
      "is_favorite": false,
      "lat": -37.816527199999996,
      "lng": 144.9691574,
      "maps_url": "https://maps.google.com/?cid=7698413963865516565",
      "cid": "7698413963865516565",
      "google_id": "/g/11bc5x8z7n"
    },
    {
      "name": "Japanese Teppanyaki Inn",
      "address": "182 Collins St, Melbourne VIC 3000, Australia",
      "note": null,
      "is_favorite": false,
      "lat": -37.814970599999995,
      "lng": 144.9674068,
      "maps_url": "https://maps.google.com/?cid=7698413962786454755",
      "cid": "7698413962786454755",
      "google_id": "/g/1tjpqmz1"
    },
    {
      "name": "Supernormal",
      "address": "180 Flinders Ln, Melbourne VIC 3000, Australia",
      "note": null,
      "is_favorite": false,
      "lat": -37.8159826,
      "lng": 144.96842089999998,
      "maps_url": "https://maps.google.com/?cid=7698413963620143413",
      "cid": "7698413963620143413",
      "google_id": "/g/11bbrm4m99"
    },
    {
      "name": "Lucy Liu Kitchen and Bar",
      "address": "23 Oliver Ln, Melbourne VIC 3000, Australia",
      "note": null,
      "is_favorite": false,
      "lat": -37.8159928,
      "lng": 144.96995379999998,
      "maps_url": "https://maps.google.com/?cid=7698413970152943455",
      "cid": "7698413970152943455",
      "google_id": "/g/11b6c65nzn"
    },
    {
      "name": "Bowery To Williamsburg",
      "address": "16 Oliver Ln, Melbourne VIC 3000, Australia",
      "note": null,
      "is_favorite": false,
      "lat": -37.8162381,
      "lng": 144.970252,
      "maps_url": "https://maps.google.com/?cid=7698413969870080567",
      "cid": "7698413969870080567",
      "google_id": "/g/12qh9qdwy"
    },
    {
      "name": "Coda Melbourne",
      "address": "Basement/141 Flinders Ln, Melbourne VIC 3000, Australia",
      "note": null,
      "is_favorite": false,
      "lat": -37.8157661,
      "lng": 144.96988969999998,
      "maps_url": "https://maps.google.com/?cid=7698413970250062837",
      "cid": "7698413970250062837",
      "google_id": "/g/1tfjwd_2"
    },
    {
      "name": "Eau De Vie Melbourne",
      "address": "1 Malthouse Ln, Melbourne VIC 3000, Australia",
      "note": null,
      "is_favorite": false,
      "lat": -37.8158003,
      "lng": 144.9715874,
      "maps_url": "https://maps.google.com/?cid=7698413971031192747",
      "cid": "7698413971031192747",
      "google_id": "/g/1q5gqrcj1"
    },
    {
      "name": "Chin Chin",
      "address": "125 Flinders Ln, Melbourne VIC 3000, Australia",
      "note": null,
      "is_favorite": false,
      "lat": -37.8155491,
      "lng": 144.9703461,
      "maps_url": "https://maps.google.com/?cid=7698413970085051903",
      "cid": "7698413970085051903",
      "google_id": "/g/11bv18x2_w"
    },
    {
      "name": "Patricia Coffee Brewers",
      "address": "Rear of, 493-495 Little Bourke St, Melbourne VIC 3000, Australia",
      "note": null,
      "is_favorite": false,
      "lat": -37.814619,
      "lng": 144.9582054,
      "maps_url": "https://maps.google.com/?cid=7698443192396698015",
      "cid": "7698443192396698015",
      "google_id": "/g/1tjg_hs3"
    },
    {
      "name": "Archie's All Day",
      "address": null,
      "note": null,
      "is_favorite": false,
      "lat": -37.806031,
      "lng": 144.9809139,
      "maps_url": "https://maps.google.com/?cid=7698414133058310601",
      "cid": "7698414133058310601",
      "google_id": null
    }
  ]
}
