{
  "fetched_at": "2026-04-15T15:26:03.664576+00:00",
  "refresh_after": "2026-04-29T15:26:03.664576+00:00",
  "source_signature": "dbc97ad3b3c0d68b8e5256f03838f1b5a3a7685729b4fb90accb255087026827",
  "configured_source_type": "google_list_url",
  "configured_source_url": "https://maps.app.goo.gl/Hr4MFQCjhpZDouhJ9",
  "configured_source_path": null,
  "source_url": "https://maps.app.goo.gl/Hr4MFQCjhpZDouhJ9",
  "list_id": "INgQXMVsAqZlC1-rViihgaZbXoD9gQ",
  "title": "Takayama, Japan 🇯🇵",
  "description": "Michael’s Takayama, Japan 🇯🇵 bookmarks. See https://beacons.ai/demflyers for more.",
  "places": [
    {
      "name": "Matsuki-Ushi",
      "address": "〒506-0009 Gifu, Takayama, Hanaokamachi, 1 Chome−17 ＡＲＣビル １Ｆ",
      "note": null,
      "is_favorite": false,
      "lat": 36.1430218,
      "lng": 137.2519919,
      "maps_url": "https://maps.google.com/?cid=6918298676608359971",
      "cid": "6918298676608359971",
      "google_id": "/g/11fpkfjxk1",
      "maps_place_token": null
    },
    {
      "name": "炒飯 花",
      "address": "〒506-0026 Gifu, Takayama, Hanasatomachi, 5 Chome−１３",
      "note": null,
      "is_favorite": false,
      "lat": 36.1413876,
      "lng": 137.2531811,
      "maps_url": "https://maps.google.com/?cid=6918297758565459373",
      "cid": "6918297758565459373",
      "google_id": "/g/11dzsprdvr",
      "maps_place_token": null
    },
    {
      "name": "Daikokuya",
      "address": "〒506-0832 Gifu, Takayama, Tenshojimachi, ２",
      "note": null,
      "is_favorite": false,
      "lat": 36.1424704,
      "lng": 137.2647537,
      "maps_url": "https://maps.google.com/?cid=6918297331031577013",
      "cid": "6918297331031577013",
      "google_id": "/g/1vc_q89l",
      "maps_place_token": null
    },
    {
      "name": "Osteria la Forchetta, Takayama",
      "address": "3 Fukiyamachi, Takayama, Gifu 506-0831",
      "note": null,
      "is_favorite": false,
      "lat": 36.1421381,
      "lng": 137.26320619999998,
      "maps_url": "https://maps.google.com/?cid=6918297332008045763",
      "cid": "6918297332008045763",
      "google_id": "/g/1vbnp9v4",
      "maps_place_token": null
    },
    {
      "name": "Kakusho",
      "address": "〒506-0838 Gifu, Takayama, Babamachi, 2 Chome−９８",
      "note": null,
      "is_favorite": false,
      "lat": 36.142344,
      "lng": 137.2624548,
      "maps_url": "https://maps.google.com/?cid=6918297428046486697",
      "cid": "6918297428046486697",
      "google_id": "/g/1tgz5dcd",
      "maps_place_token": null
    },
    {
      "name": "Nakagawa",
      "address": "33-2 Kamiichinomachi, Takayama, Gifu 506-0844",
      "note": null,
      "is_favorite": false,
      "lat": 36.1418822,
      "lng": 137.2610499,
      "maps_url": "https://maps.google.com/?cid=6918297427314177971",
      "cid": "6918297427314177971",
      "google_id": "/g/1tcv66_f",
      "maps_place_token": null
    },
    {
      "name": "Japanese Restaurant Ginputei",
      "address": "66 Kamiichinomachi, Takayama, Gifu 506-0844",
      "note": null,
      "is_favorite": false,
      "lat": 36.1426626,
      "lng": 137.2609382,
      "maps_url": "https://maps.google.com/?cid=6918431958808534641",
      "cid": "6918431958808534641",
      "google_id": "/g/1vcjm4_0",
      "maps_place_token": null
    },
    {
      "name": "Hida Takayama Gyoza Sohonzan",
      "address": "24-8 Asahimachi, Takayama, Gifu 506-0017",
      "note": null,
      "is_favorite": false,
      "lat": 36.143784,
      "lng": 137.2566336,
      "maps_url": "https://maps.google.com/?cid=6918297410628084765",
      "cid": "6918297410628084765",
      "google_id": "/g/11bxdwcrrf",
      "maps_place_token": null
    },
    {
      "name": "Tabura",
      "address": "94 Kamisannomachi, Takayama, Gifu 506-0846",
      "note": null,
      "is_favorite": false,
      "lat": 36.1414358,
      "lng": 137.25975549999998,
      "maps_url": "https://maps.google.com/?cid=6918297424342017949",
      "cid": "6918297424342017949",
      "google_id": "/g/1vqmj8qt",
      "maps_place_token": null
    },
    {
      "name": "Sakaguchiya",
      "address": "90 Kamisannomachi, Takayama, Gifu 506-0846",
      "note": null,
      "is_favorite": false,
      "lat": 36.141917899999996,
      "lng": 137.2594537,
      "maps_url": "https://maps.google.com/?cid=6918297424251597675",
      "cid": "6918297424251597675",
      "google_id": "/g/1v16q6kz",
      "maps_place_token": null
    },
    {
      "name": "Suzuya Restaurant",
      "address": "24 Hanakawamachi, Takayama, Gifu 506-0015",
      "note": null,
      "is_favorite": false,
      "lat": 36.1424136,
      "lng": 137.2556933,
      "maps_url": "https://maps.google.com/?cid=6918297412184432309",
      "cid": "6918297412184432309",
      "google_id": "/g/1tdbkxmk",
      "maps_place_token": null
    },
    {
      "name": "飛騨高山大衆居酒屋 飛騨の介",
      "address": "6 Chome-9-2 Tenmanmachi, Takayama, Gifu 506-0025",
      "note": null,
      "is_favorite": false,
      "lat": 36.1426629,
      "lng": 137.2537926,
      "maps_url": "https://maps.google.com/?cid=6918298176490853641",
      "cid": "6918298176490853641",
      "google_id": "/g/11fqy3mk_6",
      "maps_place_token": null
    },
    {
      "name": "Menya TOTO",
      "address": "〒506-0007 Gifu, Takayama, Sowamachi, 1 Chome−５０",
      "note": null,
      "is_favorite": false,
      "lat": 36.143664799999996,
      "lng": 137.2547384,
      "maps_url": "https://maps.google.com/?cid=6918297407203236833",
      "cid": "6918297407203236833",
      "google_id": "/g/1tdbqsq5",
      "maps_place_token": null
    },
    {
      "name": "旬庵",
      "address": "60 Suehiromachi, Takayama, Gifu 506-0016",
      "note": null,
      "is_favorite": false,
      "lat": 36.142902,
      "lng": 137.25541099999998,
      "maps_url": "https://maps.google.com/?cid=6918297412896045111",
      "cid": "6918297412896045111",
      "google_id": "/g/1tf3z8rk",
      "maps_place_token": null
    },
    {
      "name": "和菜蔵椿屋",
      "address": "〒506-0025 Gifu, Takayama, Hanasatomachi, 4 Chome−４８",
      "note": null,
      "is_favorite": false,
      "lat": 36.1404837,
      "lng": 137.2534249,
      "maps_url": "https://maps.google.com/?cid=6918298270152559573",
      "cid": "6918298270152559573",
      "google_id": "/g/11h3l539rm",
      "maps_place_token": null
    },
    {
      "name": "居酒家作右ヱ門",
      "address": "5 Chome-3-2 Hanasatomachi, Takayama, Gifu 506-0026",
      "note": null,
      "is_favorite": false,
      "lat": 36.1406497,
      "lng": 137.2533995,
      "maps_url": "https://maps.google.com/?cid=6918297414474350423",
      "cid": "6918297414474350423",
      "google_id": "/g/1tf28ltd",
      "maps_place_token": null
    },
    {
      "name": "Hidagyu Maruaki",
      "address": "6 Chome-8 Tenmanmachi, Takayama, Gifu 506-0025",
      "note": null,
      "is_favorite": false,
      "lat": 36.1425437,
      "lng": 137.2541783,
      "maps_url": "https://maps.google.com/?cid=6918297413464621057",
      "cid": "6918297413464621057",
      "google_id": "/g/1v3khf1d",
      "maps_place_token": null
    },
    {
      "name": "Uemura (Farm to table restaurant )",
      "address": "〒506-0025 Gifu, Takayama, Tenmanmachi, 6 Chome−６",
      "note": null,
      "is_favorite": false,
      "lat": 36.1420734,
      "lng": 137.2537805,
      "maps_url": "https://maps.google.com/?cid=6918297413887368337",
      "cid": "6918297413887368337",
      "google_id": "/g/11fx8hcrdh",
      "maps_place_token": null
    },
    {
      "name": "叶家",
      "address": "〒506-0011 Gifu, Takayama, Honmachi, 1 Chome−９３",
      "note": null,
      "is_favorite": false,
      "lat": 36.1403113,
      "lng": 137.25772609999999,
      "maps_url": "https://maps.google.com/?cid=6918297420783531709",
      "cid": "6918297420783531709",
      "google_id": "/g/1pp2wxrzv",
      "maps_place_token": null
    },
    {
      "name": "客の家料理",
      "address": "4 Chome-45-2 Tenmanmachi, Takayama, Gifu 506-0025",
      "note": null,
      "is_favorite": false,
      "lat": 36.140540099999996,
      "lng": 137.2540299,
      "maps_url": "https://maps.google.com/?cid=6918298333220611157",
      "cid": "6918298333220611157",
      "google_id": "/g/11j8p7t1tx",
      "maps_place_token": null
    },
    {
      "name": "もつ専門店 もつや",
      "address": "6 Chome-9-5 Hanasatomachi, Takayama, Gifu 506-0026",
      "note": null,
      "is_favorite": false,
      "lat": 36.142324099999996,
      "lng": 137.2529305,
      "maps_url": "https://maps.google.com/?cid=6918297758860148249",
      "cid": "6918297758860148249",
      "google_id": "/g/1tg5tzgq",
      "maps_place_token": null
    },
    {
      "name": "Aji-no-Yohei",
      "address": "〒506-0845 Gifu, Takayama, Kamisannomachi, 105番地",
      "note": null,
      "is_favorite": false,
      "lat": 36.140677499999995,
      "lng": 137.26008579999998,
      "maps_url": "https://maps.google.com/?cid=6918297430476347295",
      "cid": "6918297430476347295",
      "google_id": "/g/1thvy5r6",
      "maps_place_token": null
    },
    {
      "name": "Entaku",
      "address": "2 Chome-65 Hachikenmachi, Takayama, Gifu 506-0012",
      "note": null,
      "is_favorite": false,
      "lat": 36.1389801,
      "lng": 137.2557902,
      "maps_url": "https://maps.google.com/?cid=6918297419255785481",
      "cid": "6918297419255785481",
      "google_id": "/g/11bbx10btx",
      "maps_place_token": null
    },
    {
      "name": "PIZZERIA HIRANOGRANO",
      "address": "124 Kamikawaharamachi, Takayama, Gifu 506-0024",
      "note": null,
      "is_favorite": false,
      "lat": 36.1349004,
      "lng": 137.2565871,
      "maps_url": "https://maps.google.com/?cid=6918297441393061145",
      "cid": "6918297441393061145",
      "google_id": "/g/1v6p4674",
      "maps_place_token": null
    },
    {
      "name": "花庖丁大下本店",
      "address": "2 Chome-22 Hachikenmachi, Takayama, Gifu 506-0012",
      "note": null,
      "is_favorite": false,
      "lat": 36.1397086,
      "lng": 137.25671599999998,
      "maps_url": "https://maps.google.com/?cid=6918297418967183365",
      "cid": "6918297418967183365",
      "google_id": "/g/11btrqqblt",
      "maps_place_token": null
    },
    {
      "name": "Ajikura tengoku",
      "address": "4 Chome-308 Hanasatomachi, Takayama, Gifu 506-0026",
      "note": null,
      "is_favorite": false,
      "lat": 36.139393399999996,
      "lng": 137.2518642,
      "maps_url": "https://maps.google.com/?cid=6918297757051169451",
      "cid": "6918297757051169451",
      "google_id": "/g/1tnl19jm",
      "maps_place_token": null
    },
    {
      "name": "Yu",
      "address": "〒506-0021 Gifu, Takayama, Nadamachi, 1 Chome−49−3 県道旧41沿い",
      "note": null,
      "is_favorite": false,
      "lat": 36.1428744,
      "lng": 137.2537343,
      "maps_url": "https://maps.google.com/?cid=6918297413729556791",
      "cid": "6918297413729556791",
      "google_id": "/g/11c76k0hzd",
      "maps_place_token": null
    },
    {
      "name": "Train Bleu",
      "address": "〒506-0031 Gifu, Takayama, Nishinoisshikimachi, 1 Chome, 73~5",
      "note": null,
      "is_favorite": false,
      "lat": 36.133379,
      "lng": 137.2496941,
      "maps_url": "https://maps.google.com/?cid=6918297728348149427",
      "cid": "6918297728348149427",
      "google_id": null,
      "maps_place_token": null
    },
    {
      "name": "Sakurajaya",
      "address": "3 Chome-84-13 Sowamachi, Takayama, Gifu 506-0007",
      "note": null,
      "is_favorite": false,
      "lat": 36.1502536,
      "lng": 137.2531889,
      "maps_url": "https://maps.google.com/?cid=6918273213812834679",
      "cid": "6918273213812834679",
      "google_id": "/g/1tnpfbm4",
      "maps_place_token": null
    }
  ]
}
