{
  "fetched_at": "2026-04-15T15:21:11.321217+00:00",
  "refresh_after": "2026-04-29T15:21:11.321217+00:00",
  "source_signature": "8568da2eddebf8337434408bfb7ffa0d23e8bc241bf49ad25c6e14b35df7b684",
  "configured_source_type": "google_list_url",
  "configured_source_url": "https://maps.app.goo.gl/g7f1yVNXzMtYudbP8",
  "configured_source_path": null,
  "source_url": "https://maps.app.goo.gl/g7f1yVNXzMtYudbP8",
  "list_id": "DpMCctgERFucp7Z78EbIwg",
  "title": "Toledo, Spain 🇪🇸",
  "description": "Michael's list for Toledo, Spain 🇪🇸 See https://beacons.ai/demflyers for more.",
  "places": [
    {
      "name": "Convento de Santa Clara / Hermanas Clarisas",
      "address": null,
      "note": null,
      "is_favorite": false,
      "lat": 39.8600121,
      "lng": -4.0259529999999994,
      "maps_url": "https://maps.google.com/?cid=966597878312944829",
      "cid": "966597878312944829",
      "google_id": null,
      "maps_place_token": null
    },
    {
      "name": "Convento de Santo Domingo El Antiguo",
      "address": null,
      "note": null,
      "is_favorite": false,
      "lat": 39.8594961,
      "lng": -4.0282012,
      "maps_url": "https://maps.google.com/?cid=966597886121191123",
      "cid": "966597886121191123",
      "google_id": null,
      "maps_place_token": null
    },
    {
      "name": "San Martin's Bridge",
      "address": null,
      "note": null,
      "is_favorite": false,
      "lat": 39.856699,
      "lng": -4.0341683999999995,
      "maps_url": "https://maps.google.com/?cid=966597204060097867",
      "cid": "966597204060097867",
      "google_id": null,
      "maps_place_token": null
    },
    {
      "name": "Alcantara Bridge",
      "address": null,
      "note": null,
      "is_favorite": false,
      "lat": 39.860428,
      "lng": -4.017407599999999,
      "maps_url": "https://maps.google.com/?cid=966597966216068185",
      "cid": "966597966216068185",
      "google_id": null,
      "maps_place_token": null
    },
    {
      "name": "Museo del Greco",
      "address": null,
      "note": null,
      "is_favorite": false,
      "lat": 39.855601,
      "lng": -4.028703699999999,
      "maps_url": "https://maps.google.com/?cid=966597207335152107",
      "cid": "966597207335152107",
      "google_id": null,
      "maps_place_token": null
    },
    {
      "name": "Monasterio de San Juan de los Reyes",
      "address": null,
      "note": null,
      "is_favorite": false,
      "lat": 39.857866699999995,
      "lng": -4.031743,
      "maps_url": "https://maps.google.com/?cid=966597206182954019",
      "cid": "966597206182954019",
      "google_id": null,
      "maps_place_token": null
    },
    {
      "name": "Santa Iglesia Catedral Primada de Toledo",
      "address": null,
      "note": null,
      "is_favorite": false,
      "lat": 39.8571004,
      "lng": -4.0235688,
      "maps_url": "https://maps.google.com/?cid=966597879291589611",
      "cid": "966597879291589611",
      "google_id": null,
      "maps_place_token": null
    },
    {
      "name": "Mezquita del Cristo de la Luz",
      "address": null,
      "note": null,
      "is_favorite": false,
      "lat": 39.860576099999996,
      "lng": -4.0242506,
      "maps_url": "https://maps.google.com/?cid=966597878035705969",
      "cid": "966597878035705969",
      "google_id": null,
      "maps_place_token": null
    },
    {
      "name": "Alcázar de Toledo",
      "address": null,
      "note": null,
      "is_favorite": false,
      "lat": 39.8577545,
      "lng": -4.0204962,
      "maps_url": "https://maps.google.com/?cid=966597870458057471",
      "cid": "966597870458057471",
      "google_id": null,
      "maps_place_token": null
    },
    {
      "name": "Pl. Zocodover",
      "address": "45001 Toledo",
      "note": null,
      "is_favorite": false,
      "lat": 39.859628,
      "lng": -4.0215463,
      "maps_url": "https://maps.google.com/?cid=966597875933348611",
      "cid": "966597875933348611",
      "google_id": null,
      "maps_place_token": null
    }
  ]
}
